[
    {
        "order": 19,
        "title": "Web hacking techniques of 2021",
        "comments": 44,
        "points": 463
    },
    {
        "order": 2,
        "title": "Show HN: EdgeDB 1.0",
        "comments": 179,
        "points": 407
    },
    {
        "order": 11,
        "title": "Betty Davis has died",
        "comments": 30,
        "points": 132
    },
    {
        "order": 9,
        "title": "Structured Procrastination (1995)",
        "comments": 26,
        "points": 117
    },
    {
        "order": 24,
        "title": "Personal Stories about the TRS-80",
        "comments": 48,
        "points": 104
    },
    {
        "order": 21,
        "title": "Everything Has Fresnel (2010)",
        "comments": 17,
        "points": 83
    },
    {
        "order": 28,
        "title": "Theses on Sleep",
        "comments": 65,
        "points": 65
    },
    {
        "order": 14,
        "title": "Wordle Now Redirects to NYT",
        "comments": 43,
        "points": 48
    },
    {
        "order": 30,
        "title": "The Art World’s Spider Man",
        "comments": 0,
        "points": 8
    }
]